nn_names/__init__.py
nn_names/generator.py
nn_names/py.typed
nn_names/weights.json
nn_names/weights2.json
nn_names-1.0.0.dist-info/LICENSE
nn_names-1.0.0.dist-info/METADATA
nn_names-1.0.0.dist-info/WHEEL
nn_names-1.0.0.dist-info/top_level.txt
nn_names-1.0.0.dist-info/RECORD
