Metadata-Version: 2.1
Name: nn-names
Version: 1.0.0
Summary: A pure python package to generate random names using neural network
Author-email: Pradish Bijukchhe <pradishbijukchhe@gmail.com>
Maintainer-email: Pradish Bijukchhe <pradishbijukchhe@gmail.com>
License: Copyright (c) 2018 The Python Packaging Authority
Project-URL: Homepage, https://github.com/sandbox-pokhara/nn-names
Project-URL: Issues, https://github.com/sandbox-pokhara/nn-names/issues
Classifier: Programming Language :: Python :: 3
Requires-Python: >=3
License-File: LICENSE
